GNN/__init__.py
GNN/gnn.py
gnn_lis_kor-0.1.0.dist-info/METADATA
gnn_lis_kor-0.1.0.dist-info/WHEEL
gnn_lis_kor-0.1.0.dist-info/top_level.txt
gnn_lis_kor-0.1.0.dist-info/RECORD
