Metadata-Version: 2.2
Name: gnn-lis-kor
Version: 0.1.0
Summary: GNN HW
Author: Korneeva Elizaveta
Author-email: yanovich.liza@yandex.ru
Classifier: Programming Language :: Python :: 3
Classifier: License :: OSI Approved :: MIT License
Classifier: Operating System :: OS Independent
Requires-Python: >=3.11.11
Requires-Dist: aiohappyeyeballs==2.4.6
Requires-Dist: aiohttp==3.11.13
Requires-Dist: aiosignal==1.3.2
Requires-Dist: alembic==1.14.1
Requires-Dist: attrs==25.1.0
Requires-Dist: certifi==2025.1.31
Requires-Dist: charset-normalizer==3.4.1
Requires-Dist: colorama==0.4.6
Requires-Dist: colorlog==6.9.0
Requires-Dist: contourpy==1.3.1
Requires-Dist: cycler==0.12.1
Requires-Dist: filelock==3.17.0
Requires-Dist: fonttools==4.56.0
Requires-Dist: frozenlist==1.5.0
Requires-Dist: fsspec==2025.2.0
Requires-Dist: greenlet==3.1.1
Requires-Dist: huggingface-hub==0.29.1
Requires-Dist: idna==3.10
Requires-Dist: Jinja2==3.1.5
Requires-Dist: joblib==1.4.2
Requires-Dist: kiwisolver==1.4.8
Requires-Dist: Mako==1.3.9
Requires-Dist: MarkupSafe==3.0.2
Requires-Dist: matplotlib==3.10.0
Requires-Dist: mpmath==1.3.0
Requires-Dist: multidict==6.1.0
Requires-Dist: networkx==3.4.2
Requires-Dist: numpy==2.2.3
Requires-Dist: optuna==4.2.1
Requires-Dist: packaging==24.2
Requires-Dist: pandas==2.2.3
Requires-Dist: pillow==11.1.0
Requires-Dist: propcache==0.3.0
Requires-Dist: psutil==7.0.0
Requires-Dist: pyparsing==3.2.1
Requires-Dist: python-dateutil==2.9.0.post0
Requires-Dist: pytz==2025.1
Requires-Dist: PyYAML==6.0.2
Requires-Dist: regex==2024.11.6
Requires-Dist: requests==2.32.3
Requires-Dist: safetensors==0.5.3
Requires-Dist: scikit-learn==1.6.1
Requires-Dist: scipy==1.15.2
Requires-Dist: sentence-transformers==3.4.1
Requires-Dist: setuptools==75.8.2
Requires-Dist: six==1.17.0
Requires-Dist: SQLAlchemy==2.0.38
Requires-Dist: sympy==1.13.1
Requires-Dist: threadpoolctl==3.5.0
Requires-Dist: tokenizers==0.21.0
Requires-Dist: torch==2.6.0
Requires-Dist: torch-geometric==2.6.1
Requires-Dist: torchaudio==2.6.0
Requires-Dist: torchvision==0.21.0
Requires-Dist: tqdm==4.67.1
Requires-Dist: transformers==4.49.0
Requires-Dist: typing_extensions==4.12.2
Requires-Dist: tzdata==2025.1
Requires-Dist: urllib3==2.3.0
Requires-Dist: yarl==1.18.3
Dynamic: author
Dynamic: author-email
Dynamic: classifier
Dynamic: requires-dist
Dynamic: requires-python
Dynamic: summary
